google_internal_apis/__init__.py
google_internal_apis/cli.py
google_internal_apis/dummy_pb2.py
google_internal_apis/dummy_pb2.pyi
google_internal_apis/endpoints.py
google_internal_apis/ghunter.py
google_internal_apis/input_pb2.py
google_internal_apis/input_pb2.pyi
google_internal_apis/json_format.py
google_internal_apis/py.typed
google_internal_apis-0.6.1.dist-info/METADATA
google_internal_apis-0.6.1.dist-info/WHEEL
google_internal_apis-0.6.1.dist-info/entry_points.txt
google_internal_apis-0.6.1.dist-info/top_level.txt
google_internal_apis-0.6.1.dist-info/RECORD
