Metadata-Version: 2.2
Name: google_internal_apis
Version: 0.6.1
Summary: A wrapper around various internal (and undocumented) Google APIs that use grpc and json protobufs.
Author-email: Elliana May <me@mause.me>
License: MIT
Project-URL: repository, https://github.com/Mause/gbooks-upload
Requires-Python: <4.0,>=3.11
Requires-Dist: ghunt>=2.2.3
Requires-Dist: googleapis-common-protos>=1.66.0
Provides-Extra: cli
Requires-Dist: rich-click>=1.8.5; extra == "cli"
Requires-Dist: uvloop>=0.21.0; extra == "cli"
